gaea/__init__.py
gaea/__main__.py
goddess-0.0.1.dist-info/LICENSE
goddess-0.0.1.dist-info/WHEEL
goddess-0.0.1.dist-info/METADATA
goddess-0.0.1.dist-info/RECORD
