Metadata-Version: 2.1
Name: goddess
Version: 0.0.1
Summary: Spawn your personal website.
License: CC0-1.0
Author: Angelo Gladding
Author-email: angelo@ragt.ag
Requires-Python: >=3.9,<3.10
Classifier: License :: CC0 1.0 Universal (CC0 1.0) Public Domain Dedication
Classifier: Programming Language :: Python :: 3
Classifier: Programming Language :: Python :: 3.9
Requires-Dist: PySide6 (>=6.2.2,<7.0.0)
Requires-Dist: canopy-platform (>=0,<1)
Requires-Dist: understory (>=0,<1)
